README.md
setup.py
stats_probabilitydistribution/Binomialdistribution.py
stats_probabilitydistribution/Gaussiandistribution.py
stats_probabilitydistribution/Generaldistribution.py
stats_probabilitydistribution/__init__.py
stats_probabilitydistribution.egg-info/PKG-INFO
stats_probabilitydistribution.egg-info/SOURCES.txt
stats_probabilitydistribution.egg-info/dependency_links.txt
stats_probabilitydistribution.egg-info/not-zip-safe
stats_probabilitydistribution.egg-info/top_level.txt