Metadata-Version: 1.2
Name: stats-probabilitydistribution
Version: 0.2
Summary: Gaussian & Binomial distributions
Home-page: UNKNOWN
Author: Shubham Kumar
Author-email: shubham01kumar1@gmail.com
License: UNKNOWN
Platform: UNKNOWN
Classifier: Programming Language :: Python :: 3
Classifier: Operating System :: OS Independent
Requires-Python: >=3.6
